Kyasher/__init__.py
Kyasher/main.py
kyasher-1.5.0.dist-info/METADATA
kyasher-1.5.0.dist-info/WHEEL
kyasher-1.5.0.dist-info/top_level.txt
kyasher-1.5.0.dist-info/RECORD
