Metadata-Version: 2.1
Name: kyasher
Version: 1.5.0
Summary: An API wrapper for the KyashAPI
Home-page: https://github.com/taka-4602/Kyasher
Author: taka4602
Author-email: takaka4602@gmail.com
Keywords: kyash
Classifier: Programming Language :: Python :: 3
Classifier: License :: OSI Approved :: MIT License
Classifier: Operating System :: OS Independent
Requires-Python: >=3.6
Requires-Dist: requests
Requires-Dist: bs4
